[
  {
    "id": "D001",
    "name_ar": "فستان سهرة ذهبي",
    "name_en": "Golden Evening Dress",
    "price": 299,
    "category": "fashion"
  },
  {
    "id": "B101",
    "name_ar": "مجموعة عناية بالبشرة",
    "name_en": "Skincare Deluxe Set",
    "price": 149,
    "category": "beauty"
  },
  {
    "id": "A501",
    "name_ar": "سوار ذهبي فاخر",
    "name_en": "Luxury Gold Bracelet",
    "price": 199,
    "category": "accessories"
  },
  {
    "id": "D002",
    "name_ar": "عباية كلاسيك",
    "name_en": "Classic Abaya",
    "price": 179,
    "category": "fashion"
  },
  {
    "id": "B205",
    "name_ar": "أحمر شفاه مات",
    "name_en": "Matte Lipstick",
    "price": 29,
    "category": "beauty"
  }
]